[
  {
    "budget_consumed": 7.0,
    "hv": 13759.196146502742,
    "pareto_size": 4
  },
  {
    "budget_consumed": 12.0,
    "hv": 13759.196146502742,
    "pareto_size": 4
  },
  {
    "budget_consumed": 17.0,
    "hv": 13759.196146502742,
    "pareto_size": 4
  },
  {
    "budget_consumed": 22.0,
    "hv": 13761.222432672806,
    "pareto_size": 4
  },
  {
    "budget_consumed": 25.0,
    "hv": 13761.222432672806,
    "pareto_size": 4
  },
  {
    "budget_consumed": 25.0,
    "hv": 14273.1958389995,
    "pareto_size": 4
  }
]