[
  {
    "step": 1,
    "label": "init",
    "cost": 1.0,
    "remaining": 199.0
  },
  {
    "step": 2,
    "label": "init",
    "cost": 1.0,
    "remaining": 198.0
  },
  {
    "step": 3,
    "label": "init",
    "cost": 1.0,
    "remaining": 197.0
  },
  {
    "step": 4,
    "label": "init",
    "cost": 1.0,
    "remaining": 196.0
  },
  {
    "step": 5,
    "label": "init",
    "cost": 1.0,
    "remaining": 195.0
  },
  {
    "step": 6,
    "label": "init",
    "cost": 1.0,
    "remaining": 194.0
  },
  {
    "step": 7,
    "label": "init",
    "cost": 1.0,
    "remaining": 193.0
  },
  {
    "step": 8,
    "label": "init",
    "cost": 1.0,
    "remaining": 192.0
  },
  {
    "step": 9,
    "label": "init",
    "cost": 1.0,
    "remaining": 191.0
  },
  {
    "step": 10,
    "label": "init",
    "cost": 1.0,
    "remaining": 190.0
  },
  {
    "step": 11,
    "label": "init",
    "cost": 1.0,
    "remaining": 189.0
  },
  {
    "step": 12,
    "label": "init",
    "cost": 1.0,
    "remaining": 188.0
  },
  {
    "step": 13,
    "label": "init",
    "cost": 1.0,
    "remaining": 187.0
  },
  {
    "step": 14,
    "label": "init",
    "cost": 1.0,
    "remaining": 186.0
  },
  {
    "step": 15,
    "label": "init",
    "cost": 1.0,
    "remaining": 185.0
  },
  {
    "step": 16,
    "label": "init",
    "cost": 1.0,
    "remaining": 184.0
  },
  {
    "step": 17,
    "label": "init",
    "cost": 1.0,
    "remaining": 183.0
  },
  {
    "step": 18,
    "label": "init",
    "cost": 1.0,
    "remaining": 182.0
  },
  {
    "step": 19,
    "label": "init",
    "cost": 1.0,
    "remaining": 181.0
  },
  {
    "step": 20,
    "label": "init",
    "cost": 1.0,
    "remaining": 180.0
  },
  {
    "step": 21,
    "label": "cluster",
    "cost": 1.0,
    "remaining": 179.0
  },
  {
    "step": 22,
    "label": "mutate#0",
    "cost": 1.0,
    "remaining": 178.0
  },
  {
    "step": 23,
    "label": "crossover#0",
    "cost": 1.0,
    "remaining": 177.0
  },
  {
    "step": 24,
    "label": "mutate#0",
    "cost": 1.0,
    "remaining": 176.0
  },
  {
    "step": 25,
    "label": "crossover#0",
    "cost": 1.0,
    "remaining": 175.0
  },
  {
    "step": 26,
    "label": "mutate#0",
    "cost": 1.0,
    "remaining": 174.0
  },
  {
    "step": 27,
    "label": "crossover#0",
    "cost": 1.0,
    "remaining": 173.0
  },
  {
    "step": 28,
    "label": "mutate#1",
    "cost": 1.0,
    "remaining": 172.0
  },
  {
    "step": 29,
    "label": "mutate#2",
    "cost": 1.0,
    "remaining": 171.0
  },
  {
    "step": 30,
    "label": "crossover#1",
    "cost": 1.0,
    "remaining": 170.0
  },
  {
    "step": 31,
    "label": "mutate#0",
    "cost": 1.0,
    "remaining": 169.0
  },
  {
    "step": 32,
    "label": "cluster",
    "cost": 1.0,
    "remaining": 168.0
  },
  {
    "step": 33,
    "label": "crossover#0",
    "cost": 1.0,
    "remaining": 167.0
  },
  {
    "step": 34,
    "label": "mutate#0",
    "cost": 1.0,
    "remaining": 166.0
  },
  {
    "step": 35,
    "label": "crossover#1",
    "cost": 1.0,
    "remaining": 165.0
  },
  {
    "step": 36,
    "label": "mutate#1",
    "cost": 1.0,
    "remaining": 164.0
  },
  {
    "step": 37,
    "label": "crossover#2",
    "cost": 1.0,
    "remaining": 163.0
  },
  {
    "step": 38,
    "label": "mutate#2",
    "cost": 1.0,
    "remaining": 162.0
  },
  {
    "step": 39,
    "label": "crossover#0",
    "cost": 1.0,
    "remaining": 161.0
  },
  {
    "step": 40,
    "label": "mutate#0",
    "cost": 1.0,
    "remaining": 160.0
  },
  {
    "step": 41,
    "label": "mutate#0",
    "cost": 1.0,
    "remaining": 159.0
  },
  {
    "step": 42,
    "label": "mutate#0",
    "cost": 1.0,
    "remaining": 158.0
  },
  {
    "step": 43,
    "label": "cluster",
    "cost": 1.0,
    "remaining": 157.0
  },
  {
    "step": 44,
    "label": "mutate#0",
    "cost": 1.0,
    "remaining": 156.0
  },
  {
    "step": 45,
    "label": "mutate#1",
    "cost": 1.0,
    "remaining": 155.0
  },
  {
    "step": 46,
    "label": "mutate#3",
    "cost": 1.0,
    "remaining": 154.0
  },
  {
    "step": 47,
    "label": "mutate#2",
    "cost": 1.0,
    "remaining": 153.0
  },
  {
    "step": 48,
    "label": "mutate#4",
    "cost": 1.0,
    "remaining": 152.0
  },
  {
    "step": 49,
    "label": "mutate#0",
    "cost": 1.0,
    "remaining": 151.0
  },
  {
    "step": 50,
    "label": "crossover#0",
    "cost": 1.0,
    "remaining": 150.0
  },
  {
    "step": 51,
    "label": "crossover#1",
    "cost": 1.0,
    "remaining": 149.0
  },
  {
    "step": 52,
    "label": "crossover#3",
    "cost": 1.0,
    "remaining": 148.0
  },
  {
    "step": 53,
    "label": "crossover#2",
    "cost": 1.0,
    "remaining": 147.0
  },
  {
    "step": 54,
    "label": "cluster",
    "cost": 1.0,
    "remaining": 146.0
  },
  {
    "step": 55,
    "label": "crossover#1",
    "cost": 1.0,
    "remaining": 145.0
  },
  {
    "step": 56,
    "label": "crossover#0",
    "cost": 1.0,
    "remaining": 144.0
  },
  {
    "step": 57,
    "label": "mutate#1",
    "cost": 1.0,
    "remaining": 143.0
  },
  {
    "step": 58,
    "label": "crossover#2",
    "cost": 1.0,
    "remaining": 142.0
  },
  {
    "step": 59,
    "label": "mutate#0",
    "cost": 1.0,
    "remaining": 141.0
  },
  {
    "step": 60,
    "label": "mutate#2",
    "cost": 1.0,
    "remaining": 140.0
  },
  {
    "step": 61,
    "label": "crossover#1",
    "cost": 1.0,
    "remaining": 139.0
  },
  {
    "step": 62,
    "label": "mutate#1",
    "cost": 1.0,
    "remaining": 138.0
  },
  {
    "step": 63,
    "label": "crossover#0",
    "cost": 1.0,
    "remaining": 137.0
  },
  {
    "step": 64,
    "label": "mutate#0",
    "cost": 1.0,
    "remaining": 136.0
  },
  {
    "step": 65,
    "label": "cluster",
    "cost": 1.0,
    "remaining": 135.0
  },
  {
    "step": 66,
    "label": "crossover#1",
    "cost": 1.0,
    "remaining": 134.0
  },
  {
    "step": 67,
    "label": "mutate#1",
    "cost": 1.0,
    "remaining": 133.0
  },
  {
    "step": 68,
    "label": "crossover#0",
    "cost": 1.0,
    "remaining": 132.0
  },
  {
    "step": 69,
    "label": "mutate#0",
    "cost": 1.0,
    "remaining": 131.0
  },
  {
    "step": 70,
    "label": "mutate#2",
    "cost": 1.0,
    "remaining": 130.0
  },
  {
    "step": 71,
    "label": "mutate#3",
    "cost": 1.0,
    "remaining": 129.0
  },
  {
    "step": 72,
    "label": "crossover#2",
    "cost": 1.0,
    "remaining": 128.0
  },
  {
    "step": 73,
    "label": "mutate#0",
    "cost": 1.0,
    "remaining": 127.0
  },
  {
    "step": 74,
    "label": "crossover#3",
    "cost": 1.0,
    "remaining": 126.0
  },
  {
    "step": 75,
    "label": "mutate#0",
    "cost": 1.0,
    "remaining": 125.0
  },
  {
    "step": 76,
    "label": "cluster",
    "cost": 1.0,
    "remaining": 124.0
  },
  {
    "step": 77,
    "label": "mutate#0",
    "cost": 1.0,
    "remaining": 123.0
  },
  {
    "step": 78,
    "label": "mutate#0",
    "cost": 1.0,
    "remaining": 122.0
  },
  {
    "step": 79,
    "label": "mutate#0",
    "cost": 1.0,
    "remaining": 121.0
  },
  {
    "step": 80,
    "label": "mutate#1",
    "cost": 1.0,
    "remaining": 120.0
  },
  {
    "step": 81,
    "label": "mutate#0",
    "cost": 1.0,
    "remaining": 119.0
  },
  {
    "step": 82,
    "label": "crossover#0",
    "cost": 1.0,
    "remaining": 118.0
  },
  {
    "step": 83,
    "label": "crossover#1",
    "cost": 1.0,
    "remaining": 117.0
  },
  {
    "step": 84,
    "label": "crossover#0",
    "cost": 1.0,
    "remaining": 116.0
  },
  {
    "step": 85,
    "label": "mutate#0",
    "cost": 1.0,
    "remaining": 115.0
  },
  {
    "step": 86,
    "label": "mutate#0",
    "cost": 1.0,
    "remaining": 114.0
  },
  {
    "step": 87,
    "label": "cluster",
    "cost": 1.0,
    "remaining": 113.0
  },
  {
    "step": 88,
    "label": "mutate#0",
    "cost": 1.0,
    "remaining": 112.0
  },
  {
    "step": 89,
    "label": "mutate#1",
    "cost": 1.0,
    "remaining": 111.0
  },
  {
    "step": 90,
    "label": "mutate#0",
    "cost": 1.0,
    "remaining": 110.0
  },
  {
    "step": 91,
    "label": "crossover#0",
    "cost": 1.0,
    "remaining": 109.0
  },
  {
    "step": 92,
    "label": "mutate#1",
    "cost": 1.0,
    "remaining": 108.0
  },
  {
    "step": 93,
    "label": "crossover#1",
    "cost": 1.0,
    "remaining": 107.0
  },
  {
    "step": 94,
    "label": "mutate#0",
    "cost": 1.0,
    "remaining": 106.0
  },
  {
    "step": 95,
    "label": "mutate#1",
    "cost": 1.0,
    "remaining": 105.0
  },
  {
    "step": 96,
    "label": "crossover#0",
    "cost": 1.0,
    "remaining": 104.0
  },
  {
    "step": 97,
    "label": "mutate#0",
    "cost": 1.0,
    "remaining": 103.0
  },
  {
    "step": 98,
    "label": "cluster",
    "cost": 1.0,
    "remaining": 102.0
  },
  {
    "step": 99,
    "label": "crossover#2",
    "cost": 1.0,
    "remaining": 101.0
  },
  {
    "step": 100,
    "label": "crossover#1",
    "cost": 1.0,
    "remaining": 100.0
  },
  {
    "step": 101,
    "label": "crossover#1",
    "cost": 1.0,
    "remaining": 99.0
  },
  {
    "step": 102,
    "label": "crossover#0",
    "cost": 1.0,
    "remaining": 98.0
  },
  {
    "step": 103,
    "label": "crossover#2",
    "cost": 1.0,
    "remaining": 97.0
  },
  {
    "step": 104,
    "label": "crossover#2",
    "cost": 1.0,
    "remaining": 96.0
  },
  {
    "step": 105,
    "label": "crossover#1",
    "cost": 1.0,
    "remaining": 95.0
  },
  {
    "step": 106,
    "label": "crossover#2",
    "cost": 1.0,
    "remaining": 94.0
  },
  {
    "step": 107,
    "label": "crossover#0",
    "cost": 1.0,
    "remaining": 93.0
  },
  {
    "step": 108,
    "label": "crossover#1",
    "cost": 1.0,
    "remaining": 92.0
  },
  {
    "step": 109,
    "label": "cluster",
    "cost": 1.0,
    "remaining": 91.0
  },
  {
    "step": 110,
    "label": "crossover#0",
    "cost": 1.0,
    "remaining": 90.0
  },
  {
    "step": 111,
    "label": "crossover#1",
    "cost": 1.0,
    "remaining": 89.0
  },
  {
    "step": 112,
    "label": "crossover#2",
    "cost": 1.0,
    "remaining": 88.0
  },
  {
    "step": 113,
    "label": "crossover#2",
    "cost": 1.0,
    "remaining": 87.0
  },
  {
    "step": 114,
    "label": "crossover#2",
    "cost": 1.0,
    "remaining": 86.0
  },
  {
    "step": 115,
    "label": "crossover#2",
    "cost": 1.0,
    "remaining": 85.0
  },
  {
    "step": 116,
    "label": "crossover#2",
    "cost": 1.0,
    "remaining": 84.0
  },
  {
    "step": 117,
    "label": "crossover#2",
    "cost": 1.0,
    "remaining": 83.0
  },
  {
    "step": 118,
    "label": "crossover#2",
    "cost": 1.0,
    "remaining": 82.0
  },
  {
    "step": 119,
    "label": "crossover#2",
    "cost": 1.0,
    "remaining": 81.0
  },
  {
    "step": 120,
    "label": "cluster",
    "cost": 1.0,
    "remaining": 80.0
  },
  {
    "step": 121,
    "label": "crossover#0",
    "cost": 1.0,
    "remaining": 79.0
  },
  {
    "step": 122,
    "label": "crossover#1",
    "cost": 1.0,
    "remaining": 78.0
  },
  {
    "step": 123,
    "label": "crossover#2",
    "cost": 1.0,
    "remaining": 77.0
  },
  {
    "step": 124,
    "label": "crossover#3",
    "cost": 1.0,
    "remaining": 76.0
  },
  {
    "step": 125,
    "label": "crossover#3",
    "cost": 1.0,
    "remaining": 75.0
  },
  {
    "step": 126,
    "label": "crossover#3",
    "cost": 1.0,
    "remaining": 74.0
  },
  {
    "step": 127,
    "label": "crossover#3",
    "cost": 1.0,
    "remaining": 73.0
  },
  {
    "step": 128,
    "label": "crossover#2",
    "cost": 1.0,
    "remaining": 72.0
  },
  {
    "step": 129,
    "label": "crossover#2",
    "cost": 1.0,
    "remaining": 71.0
  },
  {
    "step": 130,
    "label": "crossover#3",
    "cost": 1.0,
    "remaining": 70.0
  },
  {
    "step": 131,
    "label": "cluster",
    "cost": 1.0,
    "remaining": 69.0
  },
  {
    "step": 132,
    "label": "crossover#0",
    "cost": 1.0,
    "remaining": 68.0
  },
  {
    "step": 133,
    "label": "crossover#1",
    "cost": 1.0,
    "remaining": 67.0
  },
  {
    "step": 134,
    "label": "crossover#3",
    "cost": 1.0,
    "remaining": 66.0
  },
  {
    "step": 135,
    "label": "crossover#2",
    "cost": 1.0,
    "remaining": 65.0
  },
  {
    "step": 136,
    "label": "crossover#4",
    "cost": 1.0,
    "remaining": 64.0
  },
  {
    "step": 137,
    "label": "crossover#0",
    "cost": 1.0,
    "remaining": 63.0
  },
  {
    "step": 138,
    "label": "crossover#0",
    "cost": 1.0,
    "remaining": 62.0
  },
  {
    "step": 139,
    "label": "crossover#0",
    "cost": 1.0,
    "remaining": 61.0
  },
  {
    "step": 140,
    "label": "crossover#4",
    "cost": 1.0,
    "remaining": 60.0
  },
  {
    "step": 141,
    "label": "crossover#4",
    "cost": 1.0,
    "remaining": 59.0
  },
  {
    "step": 142,
    "label": "cluster",
    "cost": 1.0,
    "remaining": 58.0
  },
  {
    "step": 143,
    "label": "crossover#0",
    "cost": 1.0,
    "remaining": 57.0
  },
  {
    "step": 144,
    "label": "crossover#0",
    "cost": 1.0,
    "remaining": 56.0
  },
  {
    "step": 145,
    "label": "crossover#0",
    "cost": 1.0,
    "remaining": 55.0
  },
  {
    "step": 146,
    "label": "crossover#0",
    "cost": 1.0,
    "remaining": 54.0
  },
  {
    "step": 147,
    "label": "crossover#0",
    "cost": 1.0,
    "remaining": 53.0
  },
  {
    "step": 148,
    "label": "crossover#1",
    "cost": 1.0,
    "remaining": 52.0
  },
  {
    "step": 149,
    "label": "crossover#2",
    "cost": 1.0,
    "remaining": 51.0
  },
  {
    "step": 150,
    "label": "crossover#1",
    "cost": 1.0,
    "remaining": 50.0
  },
  {
    "step": 151,
    "label": "crossover#1",
    "cost": 1.0,
    "remaining": 49.0
  },
  {
    "step": 152,
    "label": "crossover#0",
    "cost": 1.0,
    "remaining": 48.0
  },
  {
    "step": 153,
    "label": "cluster",
    "cost": 1.0,
    "remaining": 47.0
  },
  {
    "step": 154,
    "label": "crossover#0",
    "cost": 1.0,
    "remaining": 46.0
  },
  {
    "step": 155,
    "label": "crossover#1",
    "cost": 1.0,
    "remaining": 45.0
  },
  {
    "step": 156,
    "label": "crossover#2",
    "cost": 1.0,
    "remaining": 44.0
  },
  {
    "step": 157,
    "label": "crossover#0",
    "cost": 1.0,
    "remaining": 43.0
  },
  {
    "step": 158,
    "label": "crossover#0",
    "cost": 1.0,
    "remaining": 42.0
  },
  {
    "step": 159,
    "label": "crossover#1",
    "cost": 1.0,
    "remaining": 41.0
  },
  {
    "step": 160,
    "label": "mutate#0",
    "cost": 1.0,
    "remaining": 40.0
  },
  {
    "step": 161,
    "label": "crossover#2",
    "cost": 1.0,
    "remaining": 39.0
  },
  {
    "step": 162,
    "label": "crossover#0",
    "cost": 1.0,
    "remaining": 38.0
  },
  {
    "step": 163,
    "label": "mutate#1",
    "cost": 1.0,
    "remaining": 37.0
  },
  {
    "step": 164,
    "label": "cluster",
    "cost": 1.0,
    "remaining": 36.0
  },
  {
    "step": 165,
    "label": "crossover#0",
    "cost": 1.0,
    "remaining": 35.0
  },
  {
    "step": 166,
    "label": "crossover#1",
    "cost": 1.0,
    "remaining": 34.0
  },
  {
    "step": 167,
    "label": "crossover#2",
    "cost": 1.0,
    "remaining": 33.0
  },
  {
    "step": 168,
    "label": "crossover#3",
    "cost": 1.0,
    "remaining": 32.0
  },
  {
    "step": 169,
    "label": "crossover#0",
    "cost": 1.0,
    "remaining": 31.0
  },
  {
    "step": 170,
    "label": "mutate#0",
    "cost": 1.0,
    "remaining": 30.0
  },
  {
    "step": 171,
    "label": "crossover#0",
    "cost": 1.0,
    "remaining": 29.0
  },
  {
    "step": 172,
    "label": "crossover#1",
    "cost": 1.0,
    "remaining": 28.0
  },
  {
    "step": 173,
    "label": "mutate#1",
    "cost": 1.0,
    "remaining": 27.0
  },
  {
    "step": 174,
    "label": "crossover#1",
    "cost": 1.0,
    "remaining": 26.0
  },
  {
    "step": 175,
    "label": "cluster",
    "cost": 1.0,
    "remaining": 25.0
  },
  {
    "step": 176,
    "label": "mutate#0",
    "cost": 1.0,
    "remaining": 24.0
  },
  {
    "step": 177,
    "label": "crossover#0",
    "cost": 1.0,
    "remaining": 23.0
  },
  {
    "step": 178,
    "label": "crossover#1",
    "cost": 1.0,
    "remaining": 22.0
  },
  {
    "step": 179,
    "label": "mutate#1",
    "cost": 1.0,
    "remaining": 21.0
  },
  {
    "step": 180,
    "label": "crossover#2",
    "cost": 1.0,
    "remaining": 20.0
  },
  {
    "step": 181,
    "label": "crossover#2",
    "cost": 1.0,
    "remaining": 19.0
  },
  {
    "step": 182,
    "label": "crossover#2",
    "cost": 1.0,
    "remaining": 18.0
  },
  {
    "step": 183,
    "label": "crossover#2",
    "cost": 1.0,
    "remaining": 17.0
  },
  {
    "step": 184,
    "label": "crossover#2",
    "cost": 1.0,
    "remaining": 16.0
  },
  {
    "step": 185,
    "label": "crossover#2",
    "cost": 1.0,
    "remaining": 15.0
  },
  {
    "step": 186,
    "label": "cluster",
    "cost": 1.0,
    "remaining": 14.0
  },
  {
    "step": 187,
    "label": "crossover#0",
    "cost": 1.0,
    "remaining": 13.0
  },
  {
    "step": 188,
    "label": "crossover#1",
    "cost": 1.0,
    "remaining": 12.0
  },
  {
    "step": 189,
    "label": "crossover#0",
    "cost": 1.0,
    "remaining": 11.0
  },
  {
    "step": 190,
    "label": "crossover#1",
    "cost": 1.0,
    "remaining": 10.0
  },
  {
    "step": 191,
    "label": "crossover#0",
    "cost": 1.0,
    "remaining": 9.0
  },
  {
    "step": 192,
    "label": "crossover#1",
    "cost": 1.0,
    "remaining": 8.0
  },
  {
    "step": 193,
    "label": "crossover#0",
    "cost": 1.0,
    "remaining": 7.0
  },
  {
    "step": 194,
    "label": "crossover#0",
    "cost": 1.0,
    "remaining": 6.0
  },
  {
    "step": 195,
    "label": "crossover#0",
    "cost": 1.0,
    "remaining": 5.0
  },
  {
    "step": 196,
    "label": "crossover#0",
    "cost": 1.0,
    "remaining": 4.0
  },
  {
    "step": 197,
    "label": "cluster",
    "cost": 1.0,
    "remaining": 3.0
  },
  {
    "step": 198,
    "label": "crossover#0",
    "cost": 1.0,
    "remaining": 2.0
  },
  {
    "step": 199,
    "label": "crossover#0",
    "cost": 1.0,
    "remaining": 1.0
  },
  {
    "step": 200,
    "label": "crossover#0",
    "cost": 1.0,
    "remaining": 0.0
  }
]